CHANGELOG
LICENSE
PhysBiblio.exe
README.md
setup.cfg
setup.py
physbiblio/__init__.py
physbiblio/argParser.py
physbiblio/bibtexWriter.py
physbiblio/cli.py
physbiblio/config.py
physbiblio/database.py
physbiblio/databaseCore.py
physbiblio/errors.py
physbiblio/export.py
physbiblio/inspireStats.py
physbiblio/parseAccents.py
physbiblio/pdf.py
physbiblio/setuptests.py
physbiblio/tablesDef.py
physbiblio/testLoader.py
physbiblio/version.py
physbiblio/view.py
physbiblio.egg-info/PKG-INFO
physbiblio.egg-info/SOURCES.txt
physbiblio.egg-info/dependency_links.txt
physbiblio.egg-info/requires.txt
physbiblio.egg-info/top_level.txt
physbiblio/gui/__init__.py
physbiblio/gui/basicDialogs.py
physbiblio/gui/bibWindows.py
physbiblio/gui/catWindows.py
physbiblio/gui/commonClasses.py
physbiblio/gui/dialogWindows.py
physbiblio/gui/errorManager.py
physbiblio/gui/expWindows.py
physbiblio/gui/inspireStatsGUI.py
physbiblio/gui/mainWindow.py
physbiblio/gui/marks.py
physbiblio/gui/profilesManager.py
physbiblio/gui/resourcesPyside6.py
physbiblio/gui/setuptests.py
physbiblio/gui/threadElements.py
physbiblio/gui/update_resources.sh
physbiblio/gui/images/application-exit.png
physbiblio/gui/images/application-pdf.png
physbiblio/gui/images/arrow-down.png
physbiblio/gui/images/arrow-up.png
physbiblio/gui/images/delete.png
physbiblio/gui/images/dialog-error.png
physbiblio/gui/images/dialog-ok-apply.png
physbiblio/gui/images/dialog-warning.png
physbiblio/gui/images/download.png
physbiblio/gui/images/edit-clear.png
physbiblio/gui/images/edit-find-replace.png
physbiblio/gui/images/edit-node.png
physbiblio/gui/images/edit-select-all.png
physbiblio/gui/images/edit-undo.png
physbiblio/gui/images/edit-unselect-all.png
physbiblio/gui/images/edit.png
physbiblio/gui/images/emblem-favorite-symbolic.png
physbiblio/gui/images/emblem-important-symbolic.png
physbiblio/gui/images/emblem-question.png
physbiblio/gui/images/emblem-remove.png
physbiblio/gui/images/export-table.png
physbiblio/gui/images/export.png
physbiblio/gui/images/file-add.png
physbiblio/gui/images/file-save.png
physbiblio/gui/images/find.png
physbiblio/gui/images/help-about.png
physbiblio/gui/images/icon.png
