Metadata-Version: 2.1
Name: physbiblio
Version: 2.1.2
Summary: A bibliography manager in Python (using Sqlite and PySide6)
Home-page: https://github.com/steog88/PhysBiblio
Author: Stefano Gariazzo
Author-email: stefano.gariazzo@gmail.com
License: GPL-3.0
Keywords: bibliography,hep-ph,high-energy-physics,bibtex
Classifier: Development Status :: 5 - Production/Stable
Classifier: Intended Audience :: End Users/Desktop
Classifier: Intended Audience :: Science/Research
Classifier: License :: OSI Approved :: GNU General Public License v3 (GPLv3)
Classifier: Natural Language :: English
Classifier: Operating System :: OS Independent
Classifier: Programming Language :: Python
Classifier: Programming Language :: Python :: 3
Classifier: Programming Language :: Python :: 3.6
Classifier: Programming Language :: Python :: 3.7
Classifier: Programming Language :: Python :: 3.8
Classifier: Programming Language :: Python :: 3.9
Classifier: Programming Language :: Python :: 3.10
Provides: physbiblio
Provides-Extra: dev
License-File: LICENSE
